MANIFEST.in
README.rst
setup.py
django_pagseguro/__init__.py
django_pagseguro/models.py
django_pagseguro/pagseguro.py
django_pagseguro/signals.py
django_pagseguro/urls.py
django_pagseguro/views.py
django_pagseguro/templates/pagseguro_form.html
django_pagseguro/tests/__init__.py
django_pagseguro/tests/pagseguro.py
django_pagseguro/tests/signals.py
django_pagseguro/tests/views.py
django_pagseguro_v1_p3.egg-info/PKG-INFO
django_pagseguro_v1_p3.egg-info/SOURCES.txt
django_pagseguro_v1_p3.egg-info/dependency_links.txt
django_pagseguro_v1_p3.egg-info/requires.txt
django_pagseguro_v1_p3.egg-info/top_level.txt