Metadata-Version: 1.1
Name: django-pagseguro-v1-p3
Version: 1.4.2
Summary: A pluggable Django application for integrating PagSeguro payment system
Home-page: http://github.com/gustavoxpg/django-pagseguro
Author: Gustavo Fonseca
Author-email: contato@gustavofonseca.com.br
License: UNKNOWN
Platform: UNKNOWN
Classifier: Framework :: Django
Classifier: Intended Audience :: Developers
Classifier: Intended Audience :: System Administrators
Classifier: Operating System :: OS Independent
Classifier: Topic :: Software Development
Classifier: Programming Language :: Python :: 3.5
